{
  "legislative_session": "119",
  "identifier": "SRES 433",
  "title": "A resolution expressing support for the contributions and achievements of student parents in seeking and completing a postsecondary education and designating September 2025 as \"National Student Parent Month\".",
  "from_organization": "~{\"classification\": \"upper\"}",
  "classification": [
    "resolution"
  ],
  "subject": [],
  "abstracts": [],
  "other_titles": [],
  "other_identifiers": [],
  "actions": [
    {
      "description": "Submitted in the Senate, considered, and agreed to without amendment and with a preamble by Unanimous Consent.",
      "date": "2025-10-06T04:00:00+00:00",
      "organization_id": "~{\"classification\": \"upper\"}",
      "classification": [],
      "related_entities": [],
      "_processing": {
        "log_file_created": "2025-10-22T23:45:02Z"
      }
    },
    {
      "description": "Passed/agreed to in Senate: Submitted in the Senate, considered, and agreed to without amendment and with a preamble by Unanimous Consent.",
      "date": "2025-10-06T04:00:00+00:00",
      "organization_id": "~{\"classification\": \"upper\"}",
      "classification": [
        "passage"
      ],
      "related_entities": [],
      "_processing": {
        "log_file_created": "2025-10-22T23:45:02Z"
      }
    },
    {
      "description": "Introduced in Senate",
      "date": "2025-10-06T04:00:00+00:00",
      "organization_id": "~{\"classification\": \"upper\"}",
      "classification": [
        "introduction"
      ],
      "related_entities": [],
      "_processing": {
        "log_file_created": "2025-10-22T23:45:02Z"
      }
    }
  ],
  "sponsorships": [
    {
      "name": "Maggie Hassan",
      "classification": "cosponsor",
      "entity_type": "person",
      "primary": false,
      "person_id": "~{\"name\": \"Maggie Hassan\"}",
      "organization_id": null
    },
    {
      "name": "Jerry Moran",
      "classification": "primary",
      "entity_type": "person",
      "primary": true,
      "person_id": "~{\"name\": \"Jerry Moran\"}",
      "organization_id": null
    }
  ],
  "related_bills": [],
  "versions": [],
  "documents": [],
  "citations": [],
  "sources": [
    {
      "url": "https://www.govinfo.gov/bulkdata/BILLSTATUS/119/sres/BILLSTATUS-119sres433.xml",
      "note": ""
    },
    {
      "url": "https://congress.gov/bill/119th-congress/senate-resolution/433",
      "note": ""
    }
  ],
  "extras": {
    "cosponsor_bioguides": [
      "H001076"
    ],
    "sponsor_bioguides": [
      "M000934"
    ]
  },
  "jurisdiction": {
    "id": "ocd-jurisdiction/country:us/government",
    "name": "United States",
    "classification": "country",
    "division_id": "ocd-division/country:us"
  },
  "_processing": {
    "logs_latest_update": "2025-10-22T23:45:02Z",
    "text_extraction_latest_update": "2025-10-28T04:42:12.011142Z"
  }
}