{
  "legislative_session": "119",
  "identifier": "S 2334",
  "title": "Waste and Illegal Property Eradication (WIPE) Act",
  "from_organization": "~{\"classification\": \"upper\"}",
  "classification": [
    "bill"
  ],
  "subject": [],
  "abstracts": [],
  "other_titles": [
    {
      "note": "",
      "title": "A bill to authorize the use of expeditionary solid waste disposal systems by the Department of Defense and to provide funding for solid waste disposal systems, with an offset, and for other purposes."
    }
  ],
  "other_identifiers": [],
  "actions": [
    {
      "description": "Read twice and referred to the Committee on Armed Services.",
      "date": "2025-07-17T04:00:00+00:00",
      "organization_id": "~{\"classification\": \"upper\"}",
      "classification": [],
      "related_entities": [],
      "_processing": {
        "log_file_created": "2025-10-22T23:45:04Z"
      }
    },
    {
      "description": "Introduced in Senate",
      "date": "2025-07-17T04:00:00+00:00",
      "organization_id": "~{\"classification\": \"upper\"}",
      "classification": [
        "introduction"
      ],
      "related_entities": [],
      "_processing": {
        "log_file_created": "2025-10-22T23:45:04Z"
      }
    }
  ],
  "sponsorships": [
    {
      "name": "Lisa Murkowski",
      "classification": "cosponsor",
      "entity_type": "person",
      "primary": false,
      "person_id": "~{\"name\": \"Lisa Murkowski\"}",
      "organization_id": null
    },
    {
      "name": "Amy Klobuchar",
      "classification": "cosponsor",
      "entity_type": "person",
      "primary": false,
      "person_id": "~{\"name\": \"Amy Klobuchar\"}",
      "organization_id": null
    },
    {
      "name": "Thomas Roland Tillis",
      "classification": "cosponsor",
      "entity_type": "person",
      "primary": false,
      "person_id": "~{\"name\": \"Thomas Roland Tillis\"}",
      "organization_id": null
    },
    {
      "name": "Kirsten E. Gillibrand",
      "classification": "cosponsor",
      "entity_type": "person",
      "primary": false,
      "person_id": "~{\"name\": \"Kirsten E. Gillibrand\"}",
      "organization_id": null
    },
    {
      "name": "Peter Welch",
      "classification": "primary",
      "entity_type": "person",
      "primary": true,
      "person_id": "~{\"name\": \"Peter Welch\"}",
      "organization_id": null
    }
  ],
  "related_bills": [
    {
      "identifier": "HR 4526",
      "legislative_session": "119",
      "relation_type": "companion"
    }
  ],
  "versions": [
    {
      "note": "Introduced in Senate",
      "links": [
        {
          "url": "https://www.govinfo.gov/content/pkg/BILLS-119s2334is/xml/BILLS-119s2334is.xml",
          "media_type": "text/xml"
        },
        {
          "url": "https://www.govinfo.gov/content/pkg/BILLS-119s2334is/pdf/BILLS-119s2334is.pdf",
          "media_type": "application/pdf"
        }
      ],
      "date": "2025-07-17",
      "classification": ""
    }
  ],
  "documents": [],
  "citations": [],
  "sources": [
    {
      "url": "https://www.govinfo.gov/bulkdata/BILLSTATUS/119/s/BILLSTATUS-119s2334.xml",
      "note": ""
    },
    {
      "url": "https://congress.gov/bill/119th-congress/senate-bill/2334",
      "note": ""
    }
  ],
  "extras": {
    "cosponsor_bioguides": [
      "M001153",
      "K000367",
      "T000476",
      "G000555"
    ],
    "sponsor_bioguides": [
      "W000800"
    ]
  },
  "jurisdiction": {
    "id": "ocd-jurisdiction/country:us/government",
    "name": "United States",
    "classification": "country",
    "division_id": "ocd-division/country:us"
  },
  "_processing": {
    "logs_latest_update": "2025-10-22T23:45:04Z"
  }
}