{
  "legislative_session": "119",
  "identifier": "SRES 326",
  "title": "A resolution remembering the 33rd anniversary of the bombing of the Embassy of Israel in Buenos Aries on March 17, 1992, and the 31st anniversary of the bombing of the Argentine-Israeli Mutual Association building in Buenos Aires on July 18, 1994, and recommitting to efforts to uphold justice for victims of the attacks.",
  "from_organization": "~{\"classification\": \"upper\"}",
  "classification": [
    "resolution"
  ],
  "subject": [],
  "abstracts": [],
  "other_titles": [],
  "other_identifiers": [],
  "actions": [
    {
      "description": "Read twice and referred to the Committee on Foreign Relations. (text: CR S4460: 1)",
      "date": "2025-07-17T04:00:00+00:00",
      "organization_id": "~{\"classification\": \"upper\"}",
      "classification": [],
      "related_entities": []
    },
    {
      "description": "Introduced in Senate",
      "date": "2025-07-17T04:00:00+00:00",
      "organization_id": "~{\"classification\": \"upper\"}",
      "classification": [
        "introduction"
      ],
      "related_entities": []
    }
  ],
  "sponsorships": [
    {
      "name": "Jacky Rosen",
      "classification": "cosponsor",
      "entity_type": "person",
      "primary": false,
      "person_id": "~{\"name\": \"Jacky Rosen\"}",
      "organization_id": null
    },
    {
      "name": "John Curtis",
      "classification": "primary",
      "entity_type": "person",
      "primary": true,
      "person_id": "~{\"name\": \"John Curtis\"}",
      "organization_id": null
    }
  ],
  "related_bills": [],
  "versions": [
    {
      "note": "Introduced in Senate",
      "links": [
        {
          "url": "https://www.govinfo.gov/content/pkg/BILLS-119sres326is/xml/BILLS-119sres326is.xml",
          "media_type": "text/xml"
        },
        {
          "url": "https://www.govinfo.gov/content/pkg/BILLS-119sres326is/pdf/BILLS-119sres326is.pdf",
          "media_type": "application/pdf"
        }
      ],
      "date": "2025-07-17",
      "classification": ""
    }
  ],
  "documents": [],
  "citations": [],
  "sources": [
    {
      "url": "https://www.govinfo.gov/bulkdata/BILLSTATUS/119/sres/BILLSTATUS-119sres326.xml",
      "note": ""
    },
    {
      "url": "https://congress.gov/bill/119th-congress/senate-resolution/326",
      "note": ""
    }
  ],
  "extras": {
    "cosponsor_bioguides": [
      "R000608"
    ],
    "sponsor_bioguides": [
      "C001114"
    ]
  },
  "jurisdiction": {
    "id": "ocd-jurisdiction/country:us/government",
    "name": "United States",
    "classification": "country",
    "division_id": "ocd-division/country:us"
  }
}