{
  "legislative_session": "119",
  "identifier": "HR 4964",
  "title": "Child Interstate Abortion Notification Act",
  "from_organization": "~{\"classification\": \"lower\"}",
  "classification": [
    "bill"
  ],
  "subject": [],
  "abstracts": [],
  "other_titles": [
    {
      "note": "",
      "title": "To amend title 18, United States Code, to prohibit taking minors across State lines in circumvention of laws requiring the involvement of parents in abortion decisions."
    }
  ],
  "other_identifiers": [],
  "actions": [
    {
      "description": "Referred to the House Committee on the Judiciary.",
      "date": "2025-08-12T04:00:00+00:00",
      "organization_id": "~{\"classification\": \"lower\"}",
      "classification": [
        "referral-committee"
      ],
      "related_entities": [],
      "_processing": {
        "log_file_created": "2025-10-22T23:45:05Z"
      }
    },
    {
      "description": "Introduced in House",
      "date": "2025-08-12T04:00:00+00:00",
      "organization_id": "~{\"classification\": \"lower\"}",
      "classification": [
        "introduction"
      ],
      "related_entities": [],
      "_processing": {
        "log_file_created": "2025-10-22T23:45:05Z"
      }
    }
  ],
  "sponsorships": [
    {
      "name": "Robert F. Onder",
      "classification": "cosponsor",
      "entity_type": "person",
      "primary": false,
      "person_id": "~{\"name\": \"Robert F. Onder\"}",
      "organization_id": null
    },
    {
      "name": "Mark Harris",
      "classification": "cosponsor",
      "entity_type": "person",
      "primary": false,
      "person_id": "~{\"name\": \"Mark Harris\"}",
      "organization_id": null
    },
    {
      "name": "Andrew S. Clyde",
      "classification": "cosponsor",
      "entity_type": "person",
      "primary": false,
      "person_id": "~{\"name\": \"Andrew S. Clyde\"}",
      "organization_id": null
    },
    {
      "name": "Doug LaMalfa",
      "classification": "cosponsor",
      "entity_type": "person",
      "primary": false,
      "person_id": "~{\"name\": \"Doug LaMalfa\"}",
      "organization_id": null
    },
    {
      "name": "Jodey C. Arrington",
      "classification": "cosponsor",
      "entity_type": "person",
      "primary": false,
      "person_id": "~{\"name\": \"Jodey C. Arrington\"}",
      "organization_id": null
    },
    {
      "name": "Robert B. Aderholt",
      "classification": "cosponsor",
      "entity_type": "person",
      "primary": false,
      "person_id": "~{\"name\": \"Robert B. Aderholt\"}",
      "organization_id": null
    },
    {
      "name": "Mary E. Miller",
      "classification": "cosponsor",
      "entity_type": "person",
      "primary": false,
      "person_id": "~{\"name\": \"Mary E. Miller\"}",
      "organization_id": null
    },
    {
      "name": "Ron Estes",
      "classification": "cosponsor",
      "entity_type": "person",
      "primary": false,
      "person_id": "~{\"name\": \"Ron Estes\"}",
      "organization_id": null
    },
    {
      "name": "Russ Fulcher",
      "classification": "cosponsor",
      "entity_type": "person",
      "primary": false,
      "person_id": "~{\"name\": \"Russ Fulcher\"}",
      "organization_id": null
    },
    {
      "name": "Jake Ellzey",
      "classification": "cosponsor",
      "entity_type": "person",
      "primary": false,
      "person_id": "~{\"name\": \"Jake Ellzey\"}",
      "organization_id": null
    },
    {
      "name": "Christopher H. Smith",
      "classification": "cosponsor",
      "entity_type": "person",
      "primary": false,
      "person_id": "~{\"name\": \"Christopher H. Smith\"}",
      "organization_id": null
    },
    {
      "name": "Sheri Biggs",
      "classification": "cosponsor",
      "entity_type": "person",
      "primary": false,
      "person_id": "~{\"name\": \"Sheri Biggs\"}",
      "organization_id": null
    },
    {
      "name": "Michael Guest",
      "classification": "cosponsor",
      "entity_type": "person",
      "primary": false,
      "person_id": "~{\"name\": \"Michael Guest\"}",
      "organization_id": null
    },
    {
      "name": "David Rouzer",
      "classification": "cosponsor",
      "entity_type": "person",
      "primary": false,
      "person_id": "~{\"name\": \"David Rouzer\"}",
      "organization_id": null
    },
    {
      "name": "Keith Self",
      "classification": "cosponsor",
      "entity_type": "person",
      "primary": false,
      "person_id": "~{\"name\": \"Keith Self\"}",
      "organization_id": null
    },
    {
      "name": "David J. Taylor",
      "classification": "primary",
      "entity_type": "person",
      "primary": true,
      "person_id": "~{\"name\": \"David J. Taylor\"}",
      "organization_id": null
    }
  ],
  "related_bills": [],
  "versions": [
    {
      "note": "Introduced in House",
      "links": [
        {
          "url": "https://www.govinfo.gov/content/pkg/BILLS-119hr4964ih/xml/BILLS-119hr4964ih.xml",
          "media_type": "text/xml"
        },
        {
          "url": "https://www.govinfo.gov/content/pkg/BILLS-119hr4964ih/pdf/BILLS-119hr4964ih.pdf",
          "media_type": "application/pdf"
        }
      ],
      "date": "2025-08-12",
      "classification": ""
    }
  ],
  "documents": [],
  "citations": [],
  "sources": [
    {
      "url": "https://www.govinfo.gov/bulkdata/BILLSTATUS/119/hr/BILLSTATUS-119hr4964.xml",
      "note": ""
    },
    {
      "url": "https://congress.gov/bill/119th-congress/house-bill/4964",
      "note": ""
    }
  ],
  "extras": {
    "cosponsor_bioguides": [
      "O000177",
      "H001102",
      "C001116",
      "L000578",
      "A000375",
      "A000055",
      "M001211",
      "E000298",
      "F000469",
      "E000071",
      "S000522",
      "B001325",
      "G000591",
      "R000603",
      "S001224"
    ],
    "sponsor_bioguides": [
      "T000490"
    ]
  },
  "jurisdiction": {
    "id": "ocd-jurisdiction/country:us/government",
    "name": "United States",
    "classification": "country",
    "division_id": "ocd-division/country:us"
  },
  "_processing": {
    "logs_latest_update": "2025-10-22T23:45:05Z",
    "text_extraction_latest_update": "2025-10-23T20:35:38.948177Z"
  }
}