{
  "legislative_session": "119",
  "identifier": "HR 1667",
  "title": "Acupuncture for Our Seniors Act of 2025",
  "from_organization": "~{\"classification\": \"lower\"}",
  "classification": [
    "bill"
  ],
  "subject": [],
  "abstracts": [],
  "other_titles": [
    {
      "note": "",
      "title": "To amend title XVIII of the Social Security Act to provide coverage for acupuncturist services under the Medicare program."
    }
  ],
  "other_identifiers": [],
  "actions": [
    {
      "description": "Referred to the Committee on Energy and Commerce, and in addition to the Committee on Ways and Means, for a period to be subsequently determined by the Speaker, in each case for consideration of such provisions as fall within the jurisdiction of the committee concerned.",
      "date": "2025-02-27T05:00:00+00:00",
      "organization_id": "~{\"classification\": \"lower\"}",
      "classification": [
        "referral-committee"
      ],
      "related_entities": [],
      "_processing": {
        "log_file_created": "2025-10-22T23:45:07Z"
      }
    },
    {
      "description": "Introduced in House",
      "date": "2025-02-27T05:00:00+00:00",
      "organization_id": "~{\"classification\": \"lower\"}",
      "classification": [
        "introduction"
      ],
      "related_entities": [],
      "_processing": {
        "log_file_created": "2025-10-22T23:45:07Z"
      }
    }
  ],
  "sponsorships": [
    {
      "name": "Brian K. Fitzpatrick",
      "classification": "cosponsor",
      "entity_type": "person",
      "primary": false,
      "person_id": "~{\"name\": \"Brian K. Fitzpatrick\"}",
      "organization_id": null
    },
    {
      "name": "Jerrold Nadler",
      "classification": "cosponsor",
      "entity_type": "person",
      "primary": false,
      "person_id": "~{\"name\": \"Jerrold Nadler\"}",
      "organization_id": null
    },
    {
      "name": "Eleanor Holmes Norton",
      "classification": "cosponsor",
      "entity_type": "person",
      "primary": false,
      "person_id": "~{\"name\": \"Eleanor Holmes Norton\"}",
      "organization_id": null
    },
    {
      "name": "Melanie A. Stansbury",
      "classification": "cosponsor",
      "entity_type": "person",
      "primary": false,
      "person_id": "~{\"name\": \"Melanie A. Stansbury\"}",
      "organization_id": null
    },
    {
      "name": "George Whitesides",
      "classification": "cosponsor",
      "entity_type": "person",
      "primary": false,
      "person_id": "~{\"name\": \"George Whitesides\"}",
      "organization_id": null
    },
    {
      "name": "Ted Lieu",
      "classification": "cosponsor",
      "entity_type": "person",
      "primary": false,
      "person_id": "~{\"name\": \"Ted Lieu\"}",
      "organization_id": null
    },
    {
      "name": "Becca Balint",
      "classification": "cosponsor",
      "entity_type": "person",
      "primary": false,
      "person_id": "~{\"name\": \"Becca Balint\"}",
      "organization_id": null
    },
    {
      "name": "Scott H. Peters",
      "classification": "cosponsor",
      "entity_type": "person",
      "primary": false,
      "person_id": "~{\"name\": \"Scott H. Peters\"}",
      "organization_id": null
    },
    {
      "name": "Jimmy Panetta",
      "classification": "cosponsor",
      "entity_type": "person",
      "primary": false,
      "person_id": "~{\"name\": \"Jimmy Panetta\"}",
      "organization_id": null
    },
    {
      "name": "Josh Gottheimer",
      "classification": "cosponsor",
      "entity_type": "person",
      "primary": false,
      "person_id": "~{\"name\": \"Josh Gottheimer\"}",
      "organization_id": null
    },
    {
      "name": "Derek Tran",
      "classification": "cosponsor",
      "entity_type": "person",
      "primary": false,
      "person_id": "~{\"name\": \"Derek Tran\"}",
      "organization_id": null
    },
    {
      "name": "J. Luis Correa",
      "classification": "cosponsor",
      "entity_type": "person",
      "primary": false,
      "person_id": "~{\"name\": \"J. Luis Correa\"}",
      "organization_id": null
    },
    {
      "name": "Nancy Pelosi",
      "classification": "cosponsor",
      "entity_type": "person",
      "primary": false,
      "person_id": "~{\"name\": \"Nancy Pelosi\"}",
      "organization_id": null
    },
    {
      "name": "Dave Min",
      "classification": "cosponsor",
      "entity_type": "person",
      "primary": false,
      "person_id": "~{\"name\": \"Dave Min\"}",
      "organization_id": null
    },
    {
      "name": "Julia Brownley",
      "classification": "cosponsor",
      "entity_type": "person",
      "primary": false,
      "person_id": "~{\"name\": \"Julia Brownley\"}",
      "organization_id": null
    },
    {
      "name": "Judy Chu",
      "classification": "primary",
      "entity_type": "person",
      "primary": true,
      "person_id": "~{\"name\": \"Judy Chu\"}",
      "organization_id": null
    }
  ],
  "related_bills": [],
  "versions": [
    {
      "note": "Introduced in House",
      "links": [
        {
          "url": "https://www.govinfo.gov/content/pkg/BILLS-119hr1667ih/xml/BILLS-119hr1667ih.xml",
          "media_type": "text/xml"
        },
        {
          "url": "https://www.govinfo.gov/content/pkg/BILLS-119hr1667ih/pdf/BILLS-119hr1667ih.pdf",
          "media_type": "application/pdf"
        }
      ],
      "date": "2025-02-27",
      "classification": ""
    }
  ],
  "documents": [],
  "citations": [],
  "sources": [
    {
      "url": "https://www.govinfo.gov/bulkdata/BILLSTATUS/119/hr/BILLSTATUS-119hr1667.xml",
      "note": ""
    },
    {
      "url": "https://congress.gov/bill/119th-congress/house-bill/1667",
      "note": ""
    }
  ],
  "extras": {
    "cosponsor_bioguides": [
      "F000466",
      "N000002",
      "N000147",
      "S001218",
      "W000830",
      "L000582",
      "B001318",
      "P000608",
      "P000613",
      "G000583",
      "T000491",
      "C001110",
      "P000197",
      "M001241",
      "B001285"
    ],
    "sponsor_bioguides": [
      "C001080"
    ]
  },
  "jurisdiction": {
    "id": "ocd-jurisdiction/country:us/government",
    "name": "United States",
    "classification": "country",
    "division_id": "ocd-division/country:us"
  },
  "_processing": {
    "logs_latest_update": "2025-10-22T23:45:07Z"
  }
}