{
  "legislative_session": "119",
  "identifier": "S 2257",
  "title": "Legislative Branch Appropriations Act, 2026",
  "from_organization": "~{\"classification\": \"upper\"}",
  "classification": [
    "bill"
  ],
  "subject": [],
  "abstracts": [],
  "other_titles": [
    {
      "note": "",
      "title": "An original bill making appropriations for the Legislative Branch for the fiscal year ending September 30, 2026, and for other purposes."
    }
  ],
  "other_identifiers": [],
  "actions": [
    {
      "description": "Placed on Senate Legislative Calendar under General Orders. Calendar No. 113.",
      "date": "2025-07-10T04:00:00+00:00",
      "organization_id": "~{\"classification\": \"upper\"}",
      "classification": [],
      "related_entities": []
    },
    {
      "description": "Committee on Appropriations. Original measure reported to Senate by Senator Mullin. With written report No. 119-38.",
      "date": "2025-07-10T04:00:00+00:00",
      "organization_id": "~{\"classification\": \"upper\"}",
      "classification": [],
      "related_entities": []
    },
    {
      "description": "Introduced in Senate",
      "date": "2025-07-10T04:00:00+00:00",
      "organization_id": "~{\"classification\": \"upper\"}",
      "classification": [
        "introduction"
      ],
      "related_entities": []
    }
  ],
  "sponsorships": [
    {
      "name": "Markwayne Mullin",
      "classification": "primary",
      "entity_type": "person",
      "primary": true,
      "person_id": "~{\"name\": \"Markwayne Mullin\"}",
      "organization_id": null
    }
  ],
  "related_bills": [],
  "versions": [
    {
      "note": "Reported to Senate",
      "links": [
        {
          "url": "https://www.govinfo.gov/content/pkg/BILLS-119s2257rs/xml/BILLS-119s2257rs.xml",
          "media_type": "text/xml"
        },
        {
          "url": "https://www.govinfo.gov/content/pkg/BILLS-119s2257rs/pdf/BILLS-119s2257rs.pdf",
          "media_type": "application/pdf"
        }
      ],
      "date": "2025-07-10",
      "classification": ""
    }
  ],
  "documents": [
    {
      "note": "S. Rept. 119-38",
      "links": [
        {
          "url": "https://www.congress.gov/119/crpt/srpt38/CRPT-119srpt38.pdf",
          "media_type": "application/pdf"
        }
      ],
      "date": "",
      "classification": ""
    }
  ],
  "citations": [],
  "sources": [
    {
      "url": "https://www.govinfo.gov/bulkdata/BILLSTATUS/119/s/BILLSTATUS-119s2257.xml",
      "note": ""
    },
    {
      "url": "https://congress.gov/bill/119th-congress/senate-bill/2257",
      "note": ""
    }
  ],
  "extras": {
    "cosponsor_bioguides": [],
    "sponsor_bioguides": [
      "M001190"
    ]
  },
  "jurisdiction": {
    "id": "ocd-jurisdiction/country:us/government",
    "name": "United States",
    "classification": "country",
    "division_id": "ocd-division/country:us"
  }
}