{
  "legislative_session": "119",
  "identifier": "HR 3745",
  "title": "American Neighborhoods Protection Act of 2025",
  "from_organization": "~{\"classification\": \"lower\"}",
  "classification": [
    "bill"
  ],
  "subject": [],
  "abstracts": [],
  "other_titles": [
    {
      "note": "",
      "title": "To prohibit individuals and entities from owning more than 75 single-family residences, and for other purposes."
    }
  ],
  "other_identifiers": [],
  "actions": [
    {
      "description": "Referred to the Committee on Ways and Means, and in addition to the Committee on Financial Services, for a period to be subsequently determined by the Speaker, in each case for consideration of such provisions as fall within the jurisdiction of the committee concerned.",
      "date": "2025-06-05T04:00:00+00:00",
      "organization_id": "~{\"classification\": \"lower\"}",
      "classification": [
        "referral-committee"
      ],
      "related_entities": []
    },
    {
      "description": "Introduced in House",
      "date": "2025-06-05T04:00:00+00:00",
      "organization_id": "~{\"classification\": \"lower\"}",
      "classification": [
        "introduction"
      ],
      "related_entities": []
    }
  ],
  "sponsorships": [
    {
      "name": "LaMonica McIver",
      "classification": "cosponsor",
      "entity_type": "person",
      "primary": false,
      "person_id": "~{\"name\": \"LaMonica McIver\"}",
      "organization_id": null
    },
    {
      "name": "Cleo Fields",
      "classification": "cosponsor",
      "entity_type": "person",
      "primary": false,
      "person_id": "~{\"name\": \"Cleo Fields\"}",
      "organization_id": null
    },
    {
      "name": "Bennie G. Thompson",
      "classification": "cosponsor",
      "entity_type": "person",
      "primary": false,
      "person_id": "~{\"name\": \"Bennie G. Thompson\"}",
      "organization_id": null
    },
    {
      "name": "Yassamin Ansari",
      "classification": "cosponsor",
      "entity_type": "person",
      "primary": false,
      "person_id": "~{\"name\": \"Yassamin Ansari\"}",
      "organization_id": null
    },
    {
      "name": "Alma S. Adams",
      "classification": "primary",
      "entity_type": "person",
      "primary": true,
      "person_id": "~{\"name\": \"Alma S. Adams\"}",
      "organization_id": null
    }
  ],
  "related_bills": [],
  "versions": [
    {
      "note": "Introduced in House",
      "links": [
        {
          "url": "https://www.govinfo.gov/content/pkg/BILLS-119hr3745ih/xml/BILLS-119hr3745ih.xml",
          "media_type": "text/xml"
        },
        {
          "url": "https://www.govinfo.gov/content/pkg/BILLS-119hr3745ih/pdf/BILLS-119hr3745ih.pdf",
          "media_type": "application/pdf"
        }
      ],
      "date": "2025-06-05",
      "classification": ""
    }
  ],
  "documents": [],
  "citations": [],
  "sources": [
    {
      "url": "https://www.govinfo.gov/bulkdata/BILLSTATUS/119/hr/BILLSTATUS-119hr3745.xml",
      "note": ""
    },
    {
      "url": "https://congress.gov/bill/119th-congress/house-bill/3745",
      "note": ""
    }
  ],
  "extras": {
    "cosponsor_bioguides": [
      "M001229",
      "F000110",
      "T000193",
      "A000381"
    ],
    "sponsor_bioguides": [
      "A000370"
    ]
  },
  "jurisdiction": {
    "id": "ocd-jurisdiction/country:us/government",
    "name": "United States",
    "classification": "country",
    "division_id": "ocd-division/country:us"
  }
}