{
  "legislative_session": "119",
  "identifier": "HR 4446",
  "title": "FAST VETS Act",
  "from_organization": "~{\"classification\": \"lower\"}",
  "classification": [
    "bill"
  ],
  "subject": [],
  "abstracts": [],
  "other_titles": [
    {
      "note": "",
      "title": "To amend title 38, United States Code, to modify the conditions under which the Secretary of Veterans Affairs is required to redevelop the individualized vocational rehabilitation plan for a veteran, and for other purposes."
    },
    {
      "note": "",
      "title": "Focused Assistance and Skills Training for Veterans\u2019 Employment and Transition Success Act"
    }
  ],
  "other_identifiers": [],
  "actions": [
    {
      "description": "Received in the Senate and Read twice and referred to the Committee on Veterans' Affairs.",
      "date": "2025-09-16T04:00:00+00:00",
      "organization_id": "~{\"classification\": \"upper\"}",
      "classification": [],
      "related_entities": [],
      "_processing": {
        "log_file_created": "2025-10-22T23:45:02Z"
      }
    },
    {
      "description": "Motion to reconsider laid on the table Agreed to without objection.",
      "date": "2025-09-15T21:58:05+00:00",
      "organization_id": "~{\"classification\": \"lower\"}",
      "classification": [],
      "related_entities": [],
      "_processing": {
        "log_file_created": "2025-10-22T23:45:02Z"
      }
    },
    {
      "description": "On motion to suspend the rules and pass the bill Agreed to by voice vote. (text: CR H4298: 1)",
      "date": "2025-09-15T21:58:00+00:00",
      "organization_id": "~{\"classification\": \"lower\"}",
      "classification": [
        "passage"
      ],
      "related_entities": [],
      "_processing": {
        "log_file_created": "2025-10-22T23:45:02Z"
      }
    },
    {
      "description": "Passed/agreed to in House: On motion to suspend the rules and pass the bill Agreed to by voice vote. (text: CR H4298: 1)",
      "date": "2025-09-15T21:58:00+00:00",
      "organization_id": "~{\"classification\": \"lower\"}",
      "classification": [
        "passage"
      ],
      "related_entities": [],
      "_processing": {
        "log_file_created": "2025-10-22T23:45:02Z"
      }
    },
    {
      "description": "DEBATE - The House proceeded with forty minutes of debate on H.R. 4446.",
      "date": "2025-09-15T21:49:33+00:00",
      "organization_id": "~{\"classification\": \"lower\"}",
      "classification": [],
      "related_entities": [],
      "_processing": {
        "log_file_created": "2025-10-22T23:45:02Z"
      }
    },
    {
      "description": "Considered under suspension of the rules. (consideration: CR H4298)",
      "date": "2025-09-15T21:49:32+00:00",
      "organization_id": "~{\"classification\": \"lower\"}",
      "classification": [],
      "related_entities": [],
      "_processing": {
        "log_file_created": "2025-10-22T23:45:02Z"
      }
    },
    {
      "description": "Mr. Bost moved to suspend the rules and pass the bill.",
      "date": "2025-09-15T21:49:17+00:00",
      "organization_id": "~{\"classification\": \"lower\"}",
      "classification": [],
      "related_entities": [],
      "_processing": {
        "log_file_created": "2025-10-22T23:45:02Z"
      }
    },
    {
      "description": "Placed on the Union Calendar, Calendar No. 222.",
      "date": "2025-09-10T04:00:00+00:00",
      "organization_id": "~{\"classification\": \"lower\"}",
      "classification": [],
      "related_entities": [],
      "_processing": {
        "log_file_created": "2025-10-22T23:45:02Z"
      }
    },
    {
      "description": "Reported by the Committee on Veterans' Affairs. H. Rept. 119-266.",
      "date": "2025-09-10T04:00:00+00:00",
      "organization_id": "~{\"classification\": \"lower\"}",
      "classification": [],
      "related_entities": [],
      "_processing": {
        "log_file_created": "2025-10-22T23:45:02Z"
      }
    },
    {
      "description": "Ordered to be Reported by Voice Vote.",
      "date": "2025-07-23T04:00:00+00:00",
      "organization_id": "~{\"classification\": \"lower\"}",
      "classification": [],
      "related_entities": [],
      "_processing": {
        "log_file_created": "2025-10-22T23:45:02Z"
      }
    },
    {
      "description": "Committee Consideration and Mark-up Session Held",
      "date": "2025-07-23T04:00:00+00:00",
      "organization_id": "~{\"classification\": \"lower\"}",
      "classification": [],
      "related_entities": [],
      "_processing": {
        "log_file_created": "2025-10-22T23:45:02Z"
      }
    },
    {
      "description": "Referred to the House Committee on Veterans' Affairs.",
      "date": "2025-07-16T04:00:00+00:00",
      "organization_id": "~{\"classification\": \"lower\"}",
      "classification": [
        "referral-committee"
      ],
      "related_entities": [],
      "_processing": {
        "log_file_created": "2025-10-22T23:45:02Z"
      }
    },
    {
      "description": "Introduced in House",
      "date": "2025-07-16T04:00:00+00:00",
      "organization_id": "~{\"classification\": \"lower\"}",
      "classification": [
        "introduction"
      ],
      "related_entities": [],
      "_processing": {
        "log_file_created": "2025-10-22T23:45:02Z"
      }
    }
  ],
  "sponsorships": [
    {
      "name": "Mark B. Messmer",
      "classification": "cosponsor",
      "entity_type": "person",
      "primary": false,
      "person_id": "~{\"name\": \"Mark B. Messmer\"}",
      "organization_id": null
    },
    {
      "name": "Morgan McGarvey",
      "classification": "cosponsor",
      "entity_type": "person",
      "primary": false,
      "person_id": "~{\"name\": \"Morgan McGarvey\"}",
      "organization_id": null
    },
    {
      "name": "Derrick Van Orden",
      "classification": "cosponsor",
      "entity_type": "person",
      "primary": false,
      "person_id": "~{\"name\": \"Derrick Van Orden\"}",
      "organization_id": null
    },
    {
      "name": "Maxine Dexter",
      "classification": "primary",
      "entity_type": "person",
      "primary": true,
      "person_id": "~{\"name\": \"Maxine Dexter\"}",
      "organization_id": null
    }
  ],
  "related_bills": [],
  "versions": [
    {
      "note": "Referred in Senate",
      "links": [
        {
          "url": "https://www.govinfo.gov/content/pkg/BILLS-119hr4446rfs/xml/BILLS-119hr4446rfs.xml",
          "media_type": "text/xml"
        },
        {
          "url": "https://www.govinfo.gov/content/pkg/BILLS-119hr4446rfs/pdf/BILLS-119hr4446rfs.pdf",
          "media_type": "application/pdf"
        }
      ],
      "date": "2025-09-16",
      "classification": ""
    },
    {
      "note": "Engrossed in House",
      "links": [
        {
          "url": "https://www.govinfo.gov/content/pkg/BILLS-119hr4446eh/xml/BILLS-119hr4446eh.xml",
          "media_type": "text/xml"
        },
        {
          "url": "https://www.govinfo.gov/content/pkg/BILLS-119hr4446eh/pdf/BILLS-119hr4446eh.pdf",
          "media_type": "application/pdf"
        }
      ],
      "date": "2025-09-15",
      "classification": ""
    },
    {
      "note": "Reported in House",
      "links": [
        {
          "url": "https://www.govinfo.gov/content/pkg/BILLS-119hr4446rh/xml/BILLS-119hr4446rh.xml",
          "media_type": "text/xml"
        },
        {
          "url": "https://www.govinfo.gov/content/pkg/BILLS-119hr4446rh/pdf/BILLS-119hr4446rh.pdf",
          "media_type": "application/pdf"
        }
      ],
      "date": "2025-09-10",
      "classification": ""
    },
    {
      "note": "Introduced in House",
      "links": [
        {
          "url": "https://www.govinfo.gov/content/pkg/BILLS-119hr4446ih/xml/BILLS-119hr4446ih.xml",
          "media_type": "text/xml"
        },
        {
          "url": "https://www.govinfo.gov/content/pkg/BILLS-119hr4446ih/pdf/BILLS-119hr4446ih.pdf",
          "media_type": "application/pdf"
        }
      ],
      "date": "2025-07-16",
      "classification": ""
    }
  ],
  "documents": [
    {
      "note": "CBO: H.R. 4446, Focused Assistance and Skills Training for Veterans\u2019 Employment and Transition Success Act",
      "links": [
        {
          "url": "https://www.cbo.gov/publication/61654",
          "media_type": "text/html"
        }
      ],
      "date": "",
      "classification": ""
    },
    {
      "note": "H. Rept. 119-266",
      "links": [
        {
          "url": "https://www.congress.gov/119/crpt/hrpt266/CRPT-119hrpt266.pdf",
          "media_type": "application/pdf"
        }
      ],
      "date": "",
      "classification": ""
    }
  ],
  "citations": [],
  "sources": [
    {
      "url": "https://www.govinfo.gov/bulkdata/BILLSTATUS/119/hr/BILLSTATUS-119hr4446.xml",
      "note": ""
    },
    {
      "url": "https://congress.gov/bill/119th-congress/house-bill/4446",
      "note": ""
    }
  ],
  "extras": {
    "cosponsor_bioguides": [
      "M001233",
      "M001220",
      "V000135"
    ],
    "sponsor_bioguides": [
      "D000635"
    ]
  },
  "jurisdiction": {
    "id": "ocd-jurisdiction/country:us/government",
    "name": "United States",
    "classification": "country",
    "division_id": "ocd-division/country:us"
  },
  "_processing": {
    "logs_latest_update": "2025-10-22T23:45:02Z"
  }
}