{
  "legislative_session": "119",
  "identifier": "HR 2232",
  "title": "Protecting Access to Ground Ambulance Medical Services Act of 2025",
  "from_organization": "~{\"classification\": \"lower\"}",
  "classification": [
    "bill"
  ],
  "subject": [],
  "abstracts": [],
  "other_titles": [
    {
      "note": "",
      "title": "To amend title XVIII to protect patient access to ground ambulance services under part B of the Medicare program."
    }
  ],
  "other_identifiers": [],
  "actions": [
    {
      "description": "Referred to the Committee on Energy and Commerce, and in addition to the Committee on Ways and Means, for a period to be subsequently determined by the Speaker, in each case for consideration of such provisions as fall within the jurisdiction of the committee concerned.",
      "date": "2025-03-18T04:00:00+00:00",
      "organization_id": "~{\"classification\": \"lower\"}",
      "classification": [
        "referral-committee"
      ],
      "related_entities": [],
      "_processing": {
        "log_file_created": "2025-10-22T23:45:03Z"
      }
    },
    {
      "description": "Introduced in House",
      "date": "2025-03-18T04:00:00+00:00",
      "organization_id": "~{\"classification\": \"lower\"}",
      "classification": [
        "introduction"
      ],
      "related_entities": [],
      "_processing": {
        "log_file_created": "2025-10-22T23:45:03Z"
      }
    }
  ],
  "sponsorships": [
    {
      "name": "Terri A. Sewell",
      "classification": "cosponsor",
      "entity_type": "person",
      "primary": false,
      "person_id": "~{\"name\": \"Terri A. Sewell\"}",
      "organization_id": null
    },
    {
      "name": "Cliff Bentz",
      "classification": "cosponsor",
      "entity_type": "person",
      "primary": false,
      "person_id": "~{\"name\": \"Cliff Bentz\"}",
      "organization_id": null
    },
    {
      "name": "Paul Tonko",
      "classification": "cosponsor",
      "entity_type": "person",
      "primary": false,
      "person_id": "~{\"name\": \"Paul Tonko\"}",
      "organization_id": null
    },
    {
      "name": "Mike Carey",
      "classification": "cosponsor",
      "entity_type": "person",
      "primary": false,
      "person_id": "~{\"name\": \"Mike Carey\"}",
      "organization_id": null
    },
    {
      "name": "Danny K. Davis",
      "classification": "cosponsor",
      "entity_type": "person",
      "primary": false,
      "person_id": "~{\"name\": \"Danny K. Davis\"}",
      "organization_id": null
    },
    {
      "name": "Carol D. Miller",
      "classification": "cosponsor",
      "entity_type": "person",
      "primary": false,
      "person_id": "~{\"name\": \"Carol D. Miller\"}",
      "organization_id": null
    },
    {
      "name": "Marie Gluesenkamp Perez",
      "classification": "cosponsor",
      "entity_type": "person",
      "primary": false,
      "person_id": "~{\"name\": \"Marie Gluesenkamp Perez\"}",
      "organization_id": null
    },
    {
      "name": "Darin LaHood",
      "classification": "cosponsor",
      "entity_type": "person",
      "primary": false,
      "person_id": "~{\"name\": \"Darin LaHood\"}",
      "organization_id": null
    },
    {
      "name": "Elise M. Stefanik",
      "classification": "cosponsor",
      "entity_type": "person",
      "primary": false,
      "person_id": "~{\"name\": \"Elise M. Stefanik\"}",
      "organization_id": null
    },
    {
      "name": "Bryan Steil",
      "classification": "cosponsor",
      "entity_type": "person",
      "primary": false,
      "person_id": "~{\"name\": \"Bryan Steil\"}",
      "organization_id": null
    },
    {
      "name": "Glenn Thompson",
      "classification": "cosponsor",
      "entity_type": "person",
      "primary": false,
      "person_id": "~{\"name\": \"Glenn Thompson\"}",
      "organization_id": null
    },
    {
      "name": "Tracey Mann",
      "classification": "cosponsor",
      "entity_type": "person",
      "primary": false,
      "person_id": "~{\"name\": \"Tracey Mann\"}",
      "organization_id": null
    },
    {
      "name": "Janelle S. Bynum",
      "classification": "cosponsor",
      "entity_type": "person",
      "primary": false,
      "person_id": "~{\"name\": \"Janelle S. Bynum\"}",
      "organization_id": null
    },
    {
      "name": "Andrea Salinas",
      "classification": "cosponsor",
      "entity_type": "person",
      "primary": false,
      "person_id": "~{\"name\": \"Andrea Salinas\"}",
      "organization_id": null
    },
    {
      "name": "Adrian Smith",
      "classification": "cosponsor",
      "entity_type": "person",
      "primary": false,
      "person_id": "~{\"name\": \"Adrian Smith\"}",
      "organization_id": null
    },
    {
      "name": "Jared F. Golden",
      "classification": "cosponsor",
      "entity_type": "person",
      "primary": false,
      "person_id": "~{\"name\": \"Jared F. Golden\"}",
      "organization_id": null
    },
    {
      "name": "Suzanne Bonamici",
      "classification": "cosponsor",
      "entity_type": "person",
      "primary": false,
      "person_id": "~{\"name\": \"Suzanne Bonamici\"}",
      "organization_id": null
    },
    {
      "name": "Shomari Figures",
      "classification": "cosponsor",
      "entity_type": "person",
      "primary": false,
      "person_id": "~{\"name\": \"Shomari Figures\"}",
      "organization_id": null
    },
    {
      "name": "Lori Trahan",
      "classification": "cosponsor",
      "entity_type": "person",
      "primary": false,
      "person_id": "~{\"name\": \"Lori Trahan\"}",
      "organization_id": null
    },
    {
      "name": "Chrissy Houlahan",
      "classification": "cosponsor",
      "entity_type": "person",
      "primary": false,
      "person_id": "~{\"name\": \"Chrissy Houlahan\"}",
      "organization_id": null
    },
    {
      "name": "Gabe Vasquez",
      "classification": "cosponsor",
      "entity_type": "person",
      "primary": false,
      "person_id": "~{\"name\": \"Gabe Vasquez\"}",
      "organization_id": null
    },
    {
      "name": "Earl L. \"Buddy\" Carter",
      "classification": "cosponsor",
      "entity_type": "person",
      "primary": false,
      "person_id": "~{\"name\": \"Earl L. \\\"Buddy\\\" Carter\"}",
      "organization_id": null
    },
    {
      "name": "Maxine Dexter",
      "classification": "cosponsor",
      "entity_type": "person",
      "primary": false,
      "person_id": "~{\"name\": \"Maxine Dexter\"}",
      "organization_id": null
    },
    {
      "name": "Angie Craig",
      "classification": "cosponsor",
      "entity_type": "person",
      "primary": false,
      "person_id": "~{\"name\": \"Angie Craig\"}",
      "organization_id": null
    },
    {
      "name": "Janice D. Schakowsky",
      "classification": "cosponsor",
      "entity_type": "person",
      "primary": false,
      "person_id": "~{\"name\": \"Janice D. Schakowsky\"}",
      "organization_id": null
    },
    {
      "name": "Eleanor Holmes Norton",
      "classification": "cosponsor",
      "entity_type": "person",
      "primary": false,
      "person_id": "~{\"name\": \"Eleanor Holmes Norton\"}",
      "organization_id": null
    },
    {
      "name": "Brad Finstad",
      "classification": "cosponsor",
      "entity_type": "person",
      "primary": false,
      "person_id": "~{\"name\": \"Brad Finstad\"}",
      "organization_id": null
    },
    {
      "name": "Debbie Dingell",
      "classification": "cosponsor",
      "entity_type": "person",
      "primary": false,
      "person_id": "~{\"name\": \"Debbie Dingell\"}",
      "organization_id": null
    },
    {
      "name": "Rashida Tlaib",
      "classification": "cosponsor",
      "entity_type": "person",
      "primary": false,
      "person_id": "~{\"name\": \"Rashida Tlaib\"}",
      "organization_id": null
    },
    {
      "name": "Derrick Van Orden",
      "classification": "cosponsor",
      "entity_type": "person",
      "primary": false,
      "person_id": "~{\"name\": \"Derrick Van Orden\"}",
      "organization_id": null
    },
    {
      "name": "Eugene Simon Vindman",
      "classification": "cosponsor",
      "entity_type": "person",
      "primary": false,
      "person_id": "~{\"name\": \"Eugene Simon Vindman\"}",
      "organization_id": null
    },
    {
      "name": "Glenn Grothman",
      "classification": "cosponsor",
      "entity_type": "person",
      "primary": false,
      "person_id": "~{\"name\": \"Glenn Grothman\"}",
      "organization_id": null
    },
    {
      "name": "Susie Lee",
      "classification": "cosponsor",
      "entity_type": "person",
      "primary": false,
      "person_id": "~{\"name\": \"Susie Lee\"}",
      "organization_id": null
    },
    {
      "name": "Nicole Malliotakis",
      "classification": "cosponsor",
      "entity_type": "person",
      "primary": false,
      "person_id": "~{\"name\": \"Nicole Malliotakis\"}",
      "organization_id": null
    },
    {
      "name": "Pete Stauber",
      "classification": "cosponsor",
      "entity_type": "person",
      "primary": false,
      "person_id": "~{\"name\": \"Pete Stauber\"}",
      "organization_id": null
    },
    {
      "name": "Jonathan L. Jackson",
      "classification": "cosponsor",
      "entity_type": "person",
      "primary": false,
      "person_id": "~{\"name\": \"Jonathan L. Jackson\"}",
      "organization_id": null
    },
    {
      "name": "Mike Thompson",
      "classification": "cosponsor",
      "entity_type": "person",
      "primary": false,
      "person_id": "~{\"name\": \"Mike Thompson\"}",
      "organization_id": null
    },
    {
      "name": "David P. Joyce",
      "classification": "cosponsor",
      "entity_type": "person",
      "primary": false,
      "person_id": "~{\"name\": \"David P. Joyce\"}",
      "organization_id": null
    },
    {
      "name": "Michael Lawler",
      "classification": "cosponsor",
      "entity_type": "person",
      "primary": false,
      "person_id": "~{\"name\": \"Michael Lawler\"}",
      "organization_id": null
    },
    {
      "name": "Shri Thanedar",
      "classification": "cosponsor",
      "entity_type": "person",
      "primary": false,
      "person_id": "~{\"name\": \"Shri Thanedar\"}",
      "organization_id": null
    },
    {
      "name": "Eric Swalwell",
      "classification": "cosponsor",
      "entity_type": "person",
      "primary": false,
      "person_id": "~{\"name\": \"Eric Swalwell\"}",
      "organization_id": null
    },
    {
      "name": "Claudia Tenney",
      "classification": "primary",
      "entity_type": "person",
      "primary": true,
      "person_id": "~{\"name\": \"Claudia Tenney\"}",
      "organization_id": null
    }
  ],
  "related_bills": [],
  "versions": [
    {
      "note": "Introduced in House",
      "links": [
        {
          "url": "https://www.govinfo.gov/content/pkg/BILLS-119hr2232ih/xml/BILLS-119hr2232ih.xml",
          "media_type": "text/xml"
        },
        {
          "url": "https://www.govinfo.gov/content/pkg/BILLS-119hr2232ih/pdf/BILLS-119hr2232ih.pdf",
          "media_type": "application/pdf"
        }
      ],
      "date": "2025-03-18",
      "classification": ""
    }
  ],
  "documents": [],
  "citations": [],
  "sources": [
    {
      "url": "https://www.govinfo.gov/bulkdata/BILLSTATUS/119/hr/BILLSTATUS-119hr2232.xml",
      "note": ""
    },
    {
      "url": "https://congress.gov/bill/119th-congress/house-bill/2232",
      "note": ""
    }
  ],
  "extras": {
    "cosponsor_bioguides": [
      "S001185",
      "B000668",
      "T000469",
      "C001126",
      "D000096",
      "M001205",
      "G000600",
      "L000585",
      "S001196",
      "S001213",
      "T000467",
      "M000871",
      "B001326",
      "S001226",
      "S001172",
      "G000592",
      "B001278",
      "F000481",
      "T000482",
      "H001085",
      "V000136",
      "C001103",
      "D000635",
      "C001119",
      "S001145",
      "N000147",
      "F000475",
      "D000624",
      "T000481",
      "V000135",
      "V000138",
      "G000576",
      "L000590",
      "M000317",
      "S001212",
      "J000309",
      "T000460",
      "J000295",
      "L000599",
      "T000488",
      "S001193"
    ],
    "sponsor_bioguides": [
      "T000478"
    ]
  },
  "jurisdiction": {
    "id": "ocd-jurisdiction/country:us/government",
    "name": "United States",
    "classification": "country",
    "division_id": "ocd-division/country:us"
  },
  "_processing": {
    "logs_latest_update": "2025-10-22T23:45:03Z",
    "text_extraction_latest_update": "2025-10-23T20:56:54.568033Z"
  }
}