{
  "legislative_session": "119",
  "identifier": "S 2287",
  "title": "Palliative Care and Hospice Education and Training Act",
  "from_organization": "~{\"classification\": \"upper\"}",
  "classification": [
    "bill"
  ],
  "subject": [],
  "abstracts": [],
  "other_titles": [
    {
      "note": "",
      "title": "A bill to amend the Public Health Service Act to increase the number of permanent faculty in palliative care at accredited allopathic and osteopathic medical schools, nursing schools, and other programs, including social work, physician assistant, and chaplaincy education programs, to promote education and research in palliative care and hospice, and to support the development of faculty careers in academic palliative and hospice care."
    }
  ],
  "other_identifiers": [],
  "actions": [
    {
      "description": "Read twice and referred to the Committee on Health, Education, Labor, and Pensions.",
      "date": "2025-07-15T04:00:00+00:00",
      "organization_id": "~{\"classification\": \"upper\"}",
      "classification": [],
      "related_entities": [],
      "_processing": {
        "log_file_created": "2025-10-22T23:44:59Z"
      }
    },
    {
      "description": "Introduced in Senate",
      "date": "2025-07-15T04:00:00+00:00",
      "organization_id": "~{\"classification\": \"upper\"}",
      "classification": [
        "introduction"
      ],
      "related_entities": [],
      "_processing": {
        "log_file_created": "2025-10-22T23:44:59Z"
      }
    }
  ],
  "sponsorships": [
    {
      "name": "Shelley Moore Capito",
      "classification": "cosponsor",
      "entity_type": "person",
      "primary": false,
      "person_id": "~{\"name\": \"Shelley Moore Capito\"}",
      "organization_id": null
    },
    {
      "name": "Jeff Merkley",
      "classification": "cosponsor",
      "entity_type": "person",
      "primary": false,
      "person_id": "~{\"name\": \"Jeff Merkley\"}",
      "organization_id": null
    },
    {
      "name": "Roger Marshall",
      "classification": "cosponsor",
      "entity_type": "person",
      "primary": false,
      "person_id": "~{\"name\": \"Roger Marshall\"}",
      "organization_id": null
    },
    {
      "name": "Maria Cantwell",
      "classification": "cosponsor",
      "entity_type": "person",
      "primary": false,
      "person_id": "~{\"name\": \"Maria Cantwell\"}",
      "organization_id": null
    },
    {
      "name": "John Barrasso",
      "classification": "cosponsor",
      "entity_type": "person",
      "primary": false,
      "person_id": "~{\"name\": \"John Barrasso\"}",
      "organization_id": null
    },
    {
      "name": "Peter Welch",
      "classification": "cosponsor",
      "entity_type": "person",
      "primary": false,
      "person_id": "~{\"name\": \"Peter Welch\"}",
      "organization_id": null
    },
    {
      "name": "Cindy Hyde-Smith",
      "classification": "cosponsor",
      "entity_type": "person",
      "primary": false,
      "person_id": "~{\"name\": \"Cindy Hyde-Smith\"}",
      "organization_id": null
    },
    {
      "name": "John F. Reed",
      "classification": "cosponsor",
      "entity_type": "person",
      "primary": false,
      "person_id": "~{\"name\": \"John F. Reed\"}",
      "organization_id": null
    },
    {
      "name": "Mike Rounds",
      "classification": "cosponsor",
      "entity_type": "person",
      "primary": false,
      "person_id": "~{\"name\": \"Mike Rounds\"}",
      "organization_id": null
    },
    {
      "name": "Jacky Rosen",
      "classification": "cosponsor",
      "entity_type": "person",
      "primary": false,
      "person_id": "~{\"name\": \"Jacky Rosen\"}",
      "organization_id": null
    },
    {
      "name": "Lisa Murkowski",
      "classification": "cosponsor",
      "entity_type": "person",
      "primary": false,
      "person_id": "~{\"name\": \"Lisa Murkowski\"}",
      "organization_id": null
    },
    {
      "name": "Angus S. King",
      "classification": "cosponsor",
      "entity_type": "person",
      "primary": false,
      "person_id": "~{\"name\": \"Angus S. King\"}",
      "organization_id": null
    },
    {
      "name": "Marsha Blackburn",
      "classification": "cosponsor",
      "entity_type": "person",
      "primary": false,
      "person_id": "~{\"name\": \"Marsha Blackburn\"}",
      "organization_id": null
    },
    {
      "name": "Kirsten E. Gillibrand",
      "classification": "cosponsor",
      "entity_type": "person",
      "primary": false,
      "person_id": "~{\"name\": \"Kirsten E. Gillibrand\"}",
      "organization_id": null
    },
    {
      "name": "Susan M. Collins",
      "classification": "cosponsor",
      "entity_type": "person",
      "primary": false,
      "person_id": "~{\"name\": \"Susan M. Collins\"}",
      "organization_id": null
    },
    {
      "name": "Sheldon Whitehouse",
      "classification": "cosponsor",
      "entity_type": "person",
      "primary": false,
      "person_id": "~{\"name\": \"Sheldon Whitehouse\"}",
      "organization_id": null
    },
    {
      "name": "John Boozman",
      "classification": "cosponsor",
      "entity_type": "person",
      "primary": false,
      "person_id": "~{\"name\": \"John Boozman\"}",
      "organization_id": null
    },
    {
      "name": "Tina Smith",
      "classification": "cosponsor",
      "entity_type": "person",
      "primary": false,
      "person_id": "~{\"name\": \"Tina Smith\"}",
      "organization_id": null
    },
    {
      "name": "Roger F. Wicker",
      "classification": "cosponsor",
      "entity_type": "person",
      "primary": false,
      "person_id": "~{\"name\": \"Roger F. Wicker\"}",
      "organization_id": null
    },
    {
      "name": "Adam B. Schiff",
      "classification": "cosponsor",
      "entity_type": "person",
      "primary": false,
      "person_id": "~{\"name\": \"Adam B. Schiff\"}",
      "organization_id": null
    },
    {
      "name": "James C. Justice",
      "classification": "cosponsor",
      "entity_type": "person",
      "primary": false,
      "person_id": "~{\"name\": \"James C. Justice\"}",
      "organization_id": null
    },
    {
      "name": "Tammy Baldwin",
      "classification": "primary",
      "entity_type": "person",
      "primary": true,
      "person_id": "~{\"name\": \"Tammy Baldwin\"}",
      "organization_id": null
    }
  ],
  "related_bills": [
    {
      "identifier": "HR 4425",
      "legislative_session": "119",
      "relation_type": "companion"
    }
  ],
  "versions": [
    {
      "note": "Introduced in Senate",
      "links": [
        {
          "url": "https://www.govinfo.gov/content/pkg/BILLS-119s2287is/xml/BILLS-119s2287is.xml",
          "media_type": "text/xml"
        },
        {
          "url": "https://www.govinfo.gov/content/pkg/BILLS-119s2287is/pdf/BILLS-119s2287is.pdf",
          "media_type": "application/pdf"
        }
      ],
      "date": "2025-07-15",
      "classification": ""
    }
  ],
  "documents": [],
  "citations": [],
  "sources": [
    {
      "url": "https://www.govinfo.gov/bulkdata/BILLSTATUS/119/s/BILLSTATUS-119s2287.xml",
      "note": ""
    },
    {
      "url": "https://congress.gov/bill/119th-congress/senate-bill/2287",
      "note": ""
    }
  ],
  "extras": {
    "cosponsor_bioguides": [
      "C001047",
      "M001176",
      "M001198",
      "C000127",
      "B001261",
      "W000800",
      "H001079",
      "R000122",
      "R000605",
      "R000608",
      "M001153",
      "K000383",
      "B001243",
      "G000555",
      "C001035",
      "W000802",
      "B001236",
      "S001203",
      "W000437",
      "S001150",
      "J000312"
    ],
    "sponsor_bioguides": [
      "B001230"
    ]
  },
  "jurisdiction": {
    "id": "ocd-jurisdiction/country:us/government",
    "name": "United States",
    "classification": "country",
    "division_id": "ocd-division/country:us"
  },
  "_processing": {
    "logs_latest_update": "2025-10-22T23:44:59Z"
  }
}