{
  "legislative_session": "119",
  "identifier": "HR 3648",
  "title": "Transit Captions Innovations Act",
  "from_organization": "~{\"classification\": \"lower\"}",
  "classification": [
    "bill"
  ],
  "subject": [],
  "abstracts": [],
  "other_titles": [
    {
      "note": "",
      "title": "To direct the Secretary of Transportation to make grants for the deployment of innovative real-time transcription and translation technology to improve the transit rider experience for deaf, hard of hearing, and limited English proficient individuals."
    }
  ],
  "other_identifiers": [],
  "actions": [
    {
      "description": "Referred to the Subcommittee on Highways and Transit.",
      "date": "2025-05-30T04:00:00+00:00",
      "organization_id": "~{\"classification\": \"lower\"}",
      "classification": [],
      "related_entities": []
    },
    {
      "description": "Referred to the House Committee on Transportation and Infrastructure.",
      "date": "2025-05-29T04:00:00+00:00",
      "organization_id": "~{\"classification\": \"lower\"}",
      "classification": [
        "referral-committee"
      ],
      "related_entities": []
    },
    {
      "description": "Introduced in House",
      "date": "2025-05-29T04:00:00+00:00",
      "organization_id": "~{\"classification\": \"lower\"}",
      "classification": [
        "introduction"
      ],
      "related_entities": []
    }
  ],
  "sponsorships": [
    {
      "name": "Kevin Mullin",
      "classification": "primary",
      "entity_type": "person",
      "primary": true,
      "person_id": "~{\"name\": \"Kevin Mullin\"}",
      "organization_id": null
    }
  ],
  "related_bills": [],
  "versions": [
    {
      "note": "Introduced in House",
      "links": [
        {
          "url": "https://www.govinfo.gov/content/pkg/BILLS-119hr3648ih/xml/BILLS-119hr3648ih.xml",
          "media_type": "text/xml"
        },
        {
          "url": "https://www.govinfo.gov/content/pkg/BILLS-119hr3648ih/pdf/BILLS-119hr3648ih.pdf",
          "media_type": "application/pdf"
        }
      ],
      "date": "2025-05-29",
      "classification": ""
    }
  ],
  "documents": [],
  "citations": [],
  "sources": [
    {
      "url": "https://www.govinfo.gov/bulkdata/BILLSTATUS/119/hr/BILLSTATUS-119hr3648.xml",
      "note": ""
    },
    {
      "url": "https://congress.gov/bill/119th-congress/house-bill/3648",
      "note": ""
    }
  ],
  "extras": {
    "cosponsor_bioguides": [],
    "sponsor_bioguides": [
      "M001225"
    ]
  },
  "jurisdiction": {
    "id": "ocd-jurisdiction/country:us/government",
    "name": "United States",
    "classification": "country",
    "division_id": "ocd-division/country:us"
  }
}