{
  "legislative_session": "119",
  "identifier": "HR 3225",
  "title": "Belarus Democracy, Human Rights, and Sovereignty Act of 2025",
  "from_organization": "~{\"classification\": \"lower\"}",
  "classification": [
    "bill"
  ],
  "subject": [],
  "abstracts": [],
  "other_titles": [
    {
      "note": "",
      "title": "To reauthorize and modify the Belarus Democracy Act of 2004."
    }
  ],
  "other_identifiers": [],
  "actions": [
    {
      "description": "Referred to the Committee on Foreign Affairs, and in addition to the Committees on Financial Services, and the Judiciary, for a period to be subsequently determined by the Speaker, in each case for consideration of such provisions as fall within the jurisdiction of the committee concerned.",
      "date": "2025-05-07T04:00:00+00:00",
      "organization_id": "~{\"classification\": \"lower\"}",
      "classification": [
        "referral-committee"
      ],
      "related_entities": []
    },
    {
      "description": "Introduced in House",
      "date": "2025-05-07T04:00:00+00:00",
      "organization_id": "~{\"classification\": \"lower\"}",
      "classification": [
        "introduction"
      ],
      "related_entities": []
    }
  ],
  "sponsorships": [
    {
      "name": "William R. Keating",
      "classification": "cosponsor",
      "entity_type": "person",
      "primary": false,
      "person_id": "~{\"name\": \"William R. Keating\"}",
      "organization_id": null
    },
    {
      "name": "Joe Wilson",
      "classification": "cosponsor",
      "entity_type": "person",
      "primary": false,
      "person_id": "~{\"name\": \"Joe Wilson\"}",
      "organization_id": null
    },
    {
      "name": "Christopher H. Smith",
      "classification": "primary",
      "entity_type": "person",
      "primary": true,
      "person_id": "~{\"name\": \"Christopher H. Smith\"}",
      "organization_id": null
    }
  ],
  "related_bills": [
    {
      "identifier": "HR 3201",
      "legislative_session": "119",
      "relation_type": "companion"
    }
  ],
  "versions": [
    {
      "note": "Introduced in House",
      "links": [
        {
          "url": "https://www.govinfo.gov/content/pkg/BILLS-119hr3225ih/xml/BILLS-119hr3225ih.xml",
          "media_type": "text/xml"
        },
        {
          "url": "https://www.govinfo.gov/content/pkg/BILLS-119hr3225ih/pdf/BILLS-119hr3225ih.pdf",
          "media_type": "application/pdf"
        }
      ],
      "date": "2025-05-07",
      "classification": ""
    }
  ],
  "documents": [],
  "citations": [],
  "sources": [
    {
      "url": "https://www.govinfo.gov/bulkdata/BILLSTATUS/119/hr/BILLSTATUS-119hr3225.xml",
      "note": ""
    },
    {
      "url": "https://congress.gov/bill/119th-congress/house-bill/3225",
      "note": ""
    }
  ],
  "extras": {
    "cosponsor_bioguides": [
      "K000375",
      "W000795"
    ],
    "sponsor_bioguides": [
      "S000522"
    ]
  },
  "jurisdiction": {
    "id": "ocd-jurisdiction/country:us/government",
    "name": "United States",
    "classification": "country",
    "division_id": "ocd-division/country:us"
  }
}