{
  "legislative_session": "119",
  "identifier": "HR 787",
  "title": "Plain Language in Contracting Act",
  "from_organization": "~{\"classification\": \"lower\"}",
  "classification": [
    "bill"
  ],
  "subject": [],
  "abstracts": [],
  "other_titles": [
    {
      "note": "",
      "title": "To require plain language and the inclusion of key words in covered notices that are clear, concise, and accessible to small business concerns, and for other purposes."
    }
  ],
  "other_identifiers": [],
  "actions": [
    {
      "description": "Received in the Senate and Read twice and referred to the Committee on Small Business and Entrepreneurship.",
      "date": "2025-06-04T04:00:00+00:00",
      "organization_id": "~{\"classification\": \"upper\"}",
      "classification": [],
      "related_entities": []
    },
    {
      "description": "Motion to reconsider laid on the table Agreed to without objection.",
      "date": "2025-06-03T19:40:56+00:00",
      "organization_id": "~{\"classification\": \"lower\"}",
      "classification": [],
      "related_entities": []
    },
    {
      "description": "On motion to suspend the rules and pass the bill, as amended Agreed to by voice vote. (text: CR H2395)",
      "date": "2025-06-03T19:40:52+00:00",
      "organization_id": "~{\"classification\": \"lower\"}",
      "classification": [
        "passage"
      ],
      "related_entities": []
    },
    {
      "description": "Passed/agreed to in House: On motion to suspend the rules and pass the bill, as amended Agreed to by voice vote. (text: CR H2395)",
      "date": "2025-06-03T19:40:52+00:00",
      "organization_id": "~{\"classification\": \"lower\"}",
      "classification": [
        "passage"
      ],
      "related_entities": []
    },
    {
      "description": "DEBATE - The House proceeded with forty minutes of debate on H.R. 787.",
      "date": "2025-06-03T19:32:23+00:00",
      "organization_id": "~{\"classification\": \"lower\"}",
      "classification": [],
      "related_entities": []
    },
    {
      "description": "Considered under suspension of the rules. (consideration: CR H2395-2396)",
      "date": "2025-06-03T19:32:21+00:00",
      "organization_id": "~{\"classification\": \"lower\"}",
      "classification": [],
      "related_entities": []
    },
    {
      "description": "Mr. Williams (TX) moved to suspend the rules and pass the bill, as amended.",
      "date": "2025-06-03T19:32:09+00:00",
      "organization_id": "~{\"classification\": \"lower\"}",
      "classification": [],
      "related_entities": []
    },
    {
      "description": "Placed on the Union Calendar, Calendar No. 23.",
      "date": "2025-03-24T04:00:00+00:00",
      "organization_id": "~{\"classification\": \"lower\"}",
      "classification": [],
      "related_entities": []
    },
    {
      "description": "Reported (Amended) by the Committee on Small Business. H. Rept. 119-34.",
      "date": "2025-03-24T04:00:00+00:00",
      "organization_id": "~{\"classification\": \"lower\"}",
      "classification": [],
      "related_entities": []
    },
    {
      "description": "Ordered to be Reported (Amended) by the Yeas and Nays: 25 - 0.",
      "date": "2025-03-05T05:00:00+00:00",
      "organization_id": "~{\"classification\": \"lower\"}",
      "classification": [],
      "related_entities": []
    },
    {
      "description": "Committee Consideration and Mark-up Session Held",
      "date": "2025-03-05T05:00:00+00:00",
      "organization_id": "~{\"classification\": \"lower\"}",
      "classification": [],
      "related_entities": []
    },
    {
      "description": "Referred to the House Committee on Small Business.",
      "date": "2025-01-28T05:00:00+00:00",
      "organization_id": "~{\"classification\": \"lower\"}",
      "classification": [
        "referral-committee"
      ],
      "related_entities": []
    },
    {
      "description": "Introduced in House",
      "date": "2025-01-28T05:00:00+00:00",
      "organization_id": "~{\"classification\": \"lower\"}",
      "classification": [
        "introduction"
      ],
      "related_entities": []
    }
  ],
  "sponsorships": [
    {
      "name": "Derek Tran",
      "classification": "cosponsor",
      "entity_type": "person",
      "primary": false,
      "person_id": "~{\"name\": \"Derek Tran\"}",
      "organization_id": null
    },
    {
      "name": "Shri Thanedar",
      "classification": "cosponsor",
      "entity_type": "person",
      "primary": false,
      "person_id": "~{\"name\": \"Shri Thanedar\"}",
      "organization_id": null
    },
    {
      "name": "Maggie Goodlander",
      "classification": "cosponsor",
      "entity_type": "person",
      "primary": false,
      "person_id": "~{\"name\": \"Maggie Goodlander\"}",
      "organization_id": null
    },
    {
      "name": "Nick LaLota",
      "classification": "primary",
      "entity_type": "person",
      "primary": true,
      "person_id": "~{\"name\": \"Nick LaLota\"}",
      "organization_id": null
    }
  ],
  "related_bills": [],
  "versions": [
    {
      "note": "Referred in Senate",
      "links": [
        {
          "url": "https://www.govinfo.gov/content/pkg/BILLS-119hr787rfs/xml/BILLS-119hr787rfs.xml",
          "media_type": "text/xml"
        },
        {
          "url": "https://www.govinfo.gov/content/pkg/BILLS-119hr787rfs/pdf/BILLS-119hr787rfs.pdf",
          "media_type": "application/pdf"
        }
      ],
      "date": "2025-06-04",
      "classification": ""
    },
    {
      "note": "Engrossed in House",
      "links": [
        {
          "url": "https://www.govinfo.gov/content/pkg/BILLS-119hr787eh/xml/BILLS-119hr787eh.xml",
          "media_type": "text/xml"
        },
        {
          "url": "https://www.govinfo.gov/content/pkg/BILLS-119hr787eh/pdf/BILLS-119hr787eh.pdf",
          "media_type": "application/pdf"
        }
      ],
      "date": "2025-06-03",
      "classification": ""
    },
    {
      "note": "Reported in House",
      "links": [
        {
          "url": "https://www.govinfo.gov/content/pkg/BILLS-119hr787rh/xml/BILLS-119hr787rh.xml",
          "media_type": "text/xml"
        },
        {
          "url": "https://www.govinfo.gov/content/pkg/BILLS-119hr787rh/pdf/BILLS-119hr787rh.pdf",
          "media_type": "application/pdf"
        }
      ],
      "date": "2025-03-24",
      "classification": ""
    },
    {
      "note": "Introduced in House",
      "links": [
        {
          "url": "https://www.govinfo.gov/content/pkg/BILLS-119hr787ih/xml/BILLS-119hr787ih.xml",
          "media_type": "text/xml"
        },
        {
          "url": "https://www.govinfo.gov/content/pkg/BILLS-119hr787ih/pdf/BILLS-119hr787ih.pdf",
          "media_type": "application/pdf"
        }
      ],
      "date": "2025-01-28",
      "classification": ""
    }
  ],
  "documents": [
    {
      "note": "CBO: H.R. 787, Plain Language in Contracting Act",
      "links": [
        {
          "url": "https://www.cbo.gov/publication/61313",
          "media_type": "text/html"
        }
      ],
      "date": "",
      "classification": ""
    },
    {
      "note": "H. Rept. 119-34",
      "links": [
        {
          "url": "https://www.congress.gov/119/crpt/hrpt34/CRPT-119hrpt34.pdf",
          "media_type": "application/pdf"
        }
      ],
      "date": "",
      "classification": ""
    }
  ],
  "citations": [],
  "sources": [
    {
      "url": "https://www.govinfo.gov/bulkdata/BILLSTATUS/119/hr/BILLSTATUS-119hr787.xml",
      "note": ""
    },
    {
      "url": "https://congress.gov/bill/119th-congress/house-bill/787",
      "note": ""
    }
  ],
  "extras": {
    "cosponsor_bioguides": [
      "T000491",
      "T000488",
      "G000604"
    ],
    "sponsor_bioguides": [
      "L000598"
    ]
  },
  "jurisdiction": {
    "id": "ocd-jurisdiction/country:us/government",
    "name": "United States",
    "classification": "country",
    "division_id": "ocd-division/country:us"
  }
}