{
  "legislative_session": "119",
  "identifier": "HRES 555",
  "title": "Expressing support for the designation of June 28, 2025, as \"Community is Stronger than Cancer Day\".",
  "from_organization": "~{\"classification\": \"lower\"}",
  "classification": [
    "resolution"
  ],
  "subject": [],
  "abstracts": [],
  "other_titles": [],
  "other_identifiers": [],
  "actions": [
    {
      "description": "Referred to the House Committee on Energy and Commerce.",
      "date": "2025-06-27T04:00:00+00:00",
      "organization_id": "~{\"classification\": \"lower\"}",
      "classification": [
        "referral-committee"
      ],
      "related_entities": []
    },
    {
      "description": "Submitted in House",
      "date": "2025-06-27T04:00:00+00:00",
      "organization_id": "~{\"classification\": \"lower\"}",
      "classification": [
        "referral-committee"
      ],
      "related_entities": []
    }
  ],
  "sponsorships": [
    {
      "name": "Mike Kelly",
      "classification": "cosponsor",
      "entity_type": "person",
      "primary": false,
      "person_id": "~{\"name\": \"Mike Kelly\"}",
      "organization_id": null
    },
    {
      "name": "Debbie Wasserman Schultz",
      "classification": "cosponsor",
      "entity_type": "person",
      "primary": false,
      "person_id": "~{\"name\": \"Debbie Wasserman Schultz\"}",
      "organization_id": null
    },
    {
      "name": "Brian K. Fitzpatrick",
      "classification": "cosponsor",
      "entity_type": "person",
      "primary": false,
      "person_id": "~{\"name\": \"Brian K. Fitzpatrick\"}",
      "organization_id": null
    },
    {
      "name": "Debbie Dingell",
      "classification": "primary",
      "entity_type": "person",
      "primary": true,
      "person_id": "~{\"name\": \"Debbie Dingell\"}",
      "organization_id": null
    }
  ],
  "related_bills": [],
  "versions": [
    {
      "note": "Introduced in House",
      "links": [
        {
          "url": "https://www.govinfo.gov/content/pkg/BILLS-119hres555ih/xml/BILLS-119hres555ih.xml",
          "media_type": "text/xml"
        },
        {
          "url": "https://www.govinfo.gov/content/pkg/BILLS-119hres555ih/pdf/BILLS-119hres555ih.pdf",
          "media_type": "application/pdf"
        }
      ],
      "date": "2025-06-27",
      "classification": ""
    }
  ],
  "documents": [],
  "citations": [],
  "sources": [
    {
      "url": "https://www.govinfo.gov/bulkdata/BILLSTATUS/119/hres/BILLSTATUS-119hres555.xml",
      "note": ""
    },
    {
      "url": "https://congress.gov/bill/119th-congress/house-resolution/555",
      "note": ""
    }
  ],
  "extras": {
    "cosponsor_bioguides": [
      "K000376",
      "W000797",
      "F000466"
    ],
    "sponsor_bioguides": [
      "D000624"
    ]
  },
  "jurisdiction": {
    "id": "ocd-jurisdiction/country:us/government",
    "name": "United States",
    "classification": "country",
    "division_id": "ocd-division/country:us"
  }
}