{
  "legislative_session": "119",
  "identifier": "HR 5085",
  "title": "To exempt Federal actions related to the construction of infill housing from the requirements of the National Environmental Policy Act of 1969, and for other purposes.",
  "from_organization": "~{\"classification\": \"lower\"}",
  "classification": [
    "bill"
  ],
  "subject": [],
  "abstracts": [],
  "other_titles": [],
  "other_identifiers": [],
  "actions": [
    {
      "description": "Referred to the Subcommittee on Economic Development, Public Buildings, and Emergency Management.",
      "date": "2025-09-03T04:00:00+00:00",
      "organization_id": "~{\"classification\": \"lower\"}",
      "classification": [],
      "related_entities": [],
      "_processing": {
        "log_file_created": "2025-10-22T23:44:58Z"
      }
    },
    {
      "description": "Referred to the Committee on Natural Resources, and in addition to the Committee on Transportation and Infrastructure, for a period to be subsequently determined by the Speaker, in each case for consideration of such provisions as fall within the jurisdiction of the committee concerned.",
      "date": "2025-09-02T04:00:00+00:00",
      "organization_id": "~{\"classification\": \"lower\"}",
      "classification": [
        "referral-committee"
      ],
      "related_entities": [],
      "_processing": {
        "log_file_created": "2025-10-22T23:44:58Z"
      }
    },
    {
      "description": "Introduced in House",
      "date": "2025-09-02T04:00:00+00:00",
      "organization_id": "~{\"classification\": \"lower\"}",
      "classification": [
        "introduction"
      ],
      "related_entities": [],
      "_processing": {
        "log_file_created": "2025-10-22T23:44:58Z"
      }
    }
  ],
  "sponsorships": [
    {
      "name": "Chuck Edwards",
      "classification": "cosponsor",
      "entity_type": "person",
      "primary": false,
      "person_id": "~{\"name\": \"Chuck Edwards\"}",
      "organization_id": null
    },
    {
      "name": "Scott H. Peters",
      "classification": "cosponsor",
      "entity_type": "person",
      "primary": false,
      "person_id": "~{\"name\": \"Scott H. Peters\"}",
      "organization_id": null
    },
    {
      "name": "Ritchie Torres",
      "classification": "cosponsor",
      "entity_type": "person",
      "primary": false,
      "person_id": "~{\"name\": \"Ritchie Torres\"}",
      "organization_id": null
    },
    {
      "name": "Josh Harder",
      "classification": "cosponsor",
      "entity_type": "person",
      "primary": false,
      "person_id": "~{\"name\": \"Josh Harder\"}",
      "organization_id": null
    },
    {
      "name": "Seth Magaziner",
      "classification": "cosponsor",
      "entity_type": "person",
      "primary": false,
      "person_id": "~{\"name\": \"Seth Magaziner\"}",
      "organization_id": null
    },
    {
      "name": "Sharice Davids",
      "classification": "cosponsor",
      "entity_type": "person",
      "primary": false,
      "person_id": "~{\"name\": \"Sharice Davids\"}",
      "organization_id": null
    },
    {
      "name": "Jake Auchincloss",
      "classification": "cosponsor",
      "entity_type": "person",
      "primary": false,
      "person_id": "~{\"name\": \"Jake Auchincloss\"}",
      "organization_id": null
    },
    {
      "name": "Laura Friedman",
      "classification": "primary",
      "entity_type": "person",
      "primary": true,
      "person_id": "~{\"name\": \"Laura Friedman\"}",
      "organization_id": null
    }
  ],
  "related_bills": [],
  "versions": [
    {
      "note": "Introduced in House",
      "links": [
        {
          "url": "https://www.govinfo.gov/content/pkg/BILLS-119hr5085ih/xml/BILLS-119hr5085ih.xml",
          "media_type": "text/xml"
        },
        {
          "url": "https://www.govinfo.gov/content/pkg/BILLS-119hr5085ih/pdf/BILLS-119hr5085ih.pdf",
          "media_type": "application/pdf"
        }
      ],
      "date": "2025-09-02",
      "classification": ""
    }
  ],
  "documents": [],
  "citations": [],
  "sources": [
    {
      "url": "https://www.govinfo.gov/bulkdata/BILLSTATUS/119/hr/BILLSTATUS-119hr5085.xml",
      "note": ""
    },
    {
      "url": "https://congress.gov/bill/119th-congress/house-bill/5085",
      "note": ""
    }
  ],
  "extras": {
    "cosponsor_bioguides": [
      "E000246",
      "P000608",
      "T000486",
      "H001090",
      "M001223",
      "D000629",
      "A000148"
    ],
    "sponsor_bioguides": [
      "F000483"
    ]
  },
  "jurisdiction": {
    "id": "ocd-jurisdiction/country:us/government",
    "name": "United States",
    "classification": "country",
    "division_id": "ocd-division/country:us"
  },
  "_processing": {
    "logs_latest_update": "2025-10-22T23:44:58Z"
  }
}